MANIFEST.in
README.md
setup.py
rootbeerSSG/__init__.py
rootbeerSSG/create_config_file.py
rootbeerSSG/create_default_theme.py
rootbeerSSG/errors.py
rootbeerSSG/signals.py
rootbeerSSG/utils.py
rootbeerSSG.egg-info/PKG-INFO
rootbeerSSG.egg-info/SOURCES.txt
rootbeerSSG.egg-info/dependency_links.txt
rootbeerSSG.egg-info/requires.txt
rootbeerSSG.egg-info/top_level.txt