Metadata-Version: 2.1
Name: rootbeerSSG
Version: 1.0.0
Summary: The easy to use and very epic Static Site Generator for blogs!
Home-page: https://github.com/BreadcrumbIsTaken/RootbeerSSG
Author: Breadcrumb
License: MIT
Platform: UNKNOWN
Classifier: Programming Language :: Python :: 3
Classifier: Programming Language :: Python :: 3.9
Classifier: Programming Language :: Python :: 3.8
Classifier: Operating System :: OS Independent
Classifier: Natural Language :: English
Classifier: Topic :: Internet :: WWW/HTTP
Classifier: Topic :: Software Development :: Libraries :: Python Modules
Classifier: Development Status :: 5 - Production/Stable
